r7insight/__init__.py
r7insight/helpers.py
r7insight/metrics.py
r7insight/utils.py
r7insight_python-1.0.0.dist-info/METADATA
r7insight_python-1.0.0.dist-info/RECORD
r7insight_python-1.0.0.dist-info/WHEEL
r7insight_python-1.0.0.dist-info/top_level.txt
