Metadata-Version: 2.1
Name: r7insight-python
Version: 1.0.0
Summary: Python Logger plugin to send logs to Rapid7 Insight
Home-page: http://pypi.python.org/pypi/R7Insight/
Author: Rapid7
Author-email: InsightOpsTeam@rapid7.com
License: LICENSE.txt
Platform: UNKNOWN
Classifier: Intended Audience :: Developers
Classifier: License :: OSI Approved :: MIT License
Classifier: Operating System :: OS Independent
Classifier: Programming Language :: Python :: 2
Classifier: Programming Language :: Python :: 3
Requires-Dist: certifi
